cloudhive/__init__.py
cloudhive/exceptions.py
cloudhive/request_dispatcher.py
cloudhive/rich_logger.py
cloudhive/utils.py
cloudhive/display/__init__.py
cloudhive/display/console.py
cloudhive/display/template.py
cloudhive/models/__init__.py
cloudhive/models/http_res.py
cloudhive-1.1.0.dist-info/LICENSE
cloudhive-1.1.0.dist-info/METADATA
cloudhive-1.1.0.dist-info/WHEEL
cloudhive-1.1.0.dist-info/top_level.txt
cloudhive-1.1.0.dist-info/RECORD
