Metadata-Version: 2.2
Name: cloudhive
Version: 1.1.0
Summary: Some Useful Utils package
Author-email: Nitin Namdev <itsmyidbro@gmail.com>
Project-URL: Homepage, https://github.com/vortexdude/PyKit
Project-URL: Issues, https://github.com/vortexdude/PyKit/issues
Classifier: Programming Language :: Python :: 3.13
Classifier: License :: OSI Approved :: MIT License
Classifier: Operating System :: OS Independent
Requires-Python: >=3.13
License-File: LICENSE
Requires-Dist: certifi==2024.12.14
Requires-Dist: charset-normalizer==3.4.0
Requires-Dist: idna==3.10
Requires-Dist: markdown-it-py==3.0.0
Requires-Dist: mdurl==0.1.2
Requires-Dist: Pygments==2.18.0
Requires-Dist: PyYAML==6.0.2
Requires-Dist: requests==2.32.3
Requires-Dist: rich==13.9.4
Requires-Dist: urllib3==2.2.3
